[
  {
    "name": "The Sky Bar",
    "category": 5,
    "concept": ["Comida rápida", "Temático", "Para llevar"]
  },
  {
    "name": "Cantina Rápida",
    "category": 4,
    "concept": ["Comida rápida", "Buffet", "Familiar"]
  },
  {
    "name": "Raíces",
    "category": 4,
    "concept": ["Temático", "Familiar", "Gourmet"]
  },
  {
    "name": "Avenida del Sabor",
    "category": 3,
    "concept": ["Gourmet"]
  },
  {
    "name": "Bella Mia Italian",
    "category": 4,
    "concept": ["Temático", "Familiar", "Gourmet"]
  },
  {
    "name": "Taco on the Plaza",
    "category": 3,
    "concept": ["Comida rápida"]
  },
  {
    "name": "Street Food",
    "category": 4,
    "concept": ["Familiar"]
  },
  {
    "name": "Terra Viva",
    "category": 2,
    "concept": ["Para llevar", "Familiar", "Buffet"]
  },
  {
    "name": "Pasta La Rose!",
    "category": 3,
    "concept": ["Temático"]
  },
  {
    "name": "The Cucina",
    "category": 3,
    "concept": ["Familiar", "Temático", "Para llevar"]
  }
]
